<annotation>
	<folder>frames</folder>
	<filename>143.jpg</filename>
	<path>/media/anuj/Work-HDD/ZigZag_Bike/Zig Zag vehicle_24-04-19/data/1/frames/143.jpg</path>
	<source>
		<database>Unknown</database>
	</source>
	<size>
		<width>1920</width>
		<height>1080</height>
		<depth>3</depth>
	</size>
	<segmented>0</segmented>
	<object>
		<name>2Wheeler</name>
		<pose>Unspecified</pose>
		<truncated>0</truncated>
		<difficult>0</difficult>
		<bndbox>
			<xmin>600</xmin>
			<ymin>142</ymin>
			<xmax>646</xmax>
			<ymax>252</ymax>
		</bndbox>
	</object>
	<object>
		<name>2Wheeler</name>
		<pose>Unspecified</pose>
		<truncated>0</truncated>
		<difficult>0</difficult>
		<bndbox>
			<xmin>595</xmin>
			<ymin>140</ymin>
			<xmax>641</xmax>
			<ymax>250</ymax>
		</bndbox>
	</object>
	<object>
		<name>2Wheeler</name>
		<pose>Unspecified</pose>
		<truncated>0</truncated>
		<difficult>0</difficult>
		<bndbox>
			<xmin>952</xmin>
			<ymin>188</ymin>
			<xmax>1044</xmax>
			<ymax>330</ymax>
		</bndbox>
	</object>
	<object>
		<name>2Wheeler</name>
		<pose>Unspecified</pose>
		<truncated>0</truncated>
		<difficult>0</difficult>
		<bndbox>
			<xmin>976</xmin>
			<ymin>366</ymin>
			<xmax>1043</xmax>
			<ymax>566</ymax>
		</bndbox>
	</object>
	<object>
		<name>2Wheeler</name>
		<pose>Unspecified</pose>
		<truncated>0</truncated>
		<difficult>0</difficult>
		<bndbox>
			<xmin>1037</xmin>
			<ymin>488</ymin>
			<xmax>1146</xmax>
			<ymax>732</ymax>
		</bndbox>
	</object>
	<object>
		<name>2Wheeler</name>
		<pose>Unspecified</pose>
		<truncated>0</truncated>
		<difficult>0</difficult>
		<bndbox>
			<xmin>793</xmin>
			<ymin>34</ymin>
			<xmax>832</xmax>
			<ymax>104</ymax>
		</bndbox>
	</object>
</annotation>
